Metadata-Version: 1.0
Name: shrun
Version: 0.6.0
Summary: shrun yaml-based runner
Home-page: https://https://git.corp.nextdoor.com/Nextdoor/nd-shrun
Author: Dev Tools Team
Author-email: asbrown@nextdoor.com
License: UNKNOWN
Platform: UNKNOWN
